utt_balance/__init__.py
utt/plugins/balance.py
utt_balance-0.1.1.dist-info/METADATA
utt_balance-0.1.1.dist-info/WHEEL
utt_balance-0.1.1.dist-info/licenses/LICENSE
utt_balance-0.1.1.dist-info/RECORD
